pds_web_analytics-1.0.1-py3.13-nspkg.pth
pds/web_analytics/VERSION.txt
pds/web_analytics/__init__.py
pds/web_analytics/s3_sync.py
pds_web_analytics-1.0.1.dist-info/licenses/LICENSE.md
pds_web_analytics-1.0.1.dist-info/licenses/NOTICE.txt
pds_web_analytics-1.0.1.dist-info/METADATA
pds_web_analytics-1.0.1.dist-info/WHEEL
pds_web_analytics-1.0.1.dist-info/entry_points.txt
pds_web_analytics-1.0.1.dist-info/namespace_packages.txt
pds_web_analytics-1.0.1.dist-info/top_level.txt
pds_web_analytics-1.0.1.dist-info/zip-safe
pds_web_analytics-1.0.1.dist-info/RECORD
