Metadata-Version: 2.4
Name: pds-web-analytics
Version: 1.0.1
Summary: PDS Web Analytics - Log processing and S3 synchronization for Planetary Data System
Home-page: https://github.com/NASA-PDS/web-analytics
Download-URL: https://github.com/NASA-PDS/web-analytics/releases/
Author: PDS
Author-email: pds_operator@jpl.nasa.gov
License: apache-2.0
Keywords: pds,planetary data,web analytics,logstash,s3,aws
Classifier: Programming Language :: Python :: 3
Classifier: Programming Language :: Python :: 3.12
Classifier: Programming Language :: Python :: 3.13
Classifier: License :: OSI Approved :: Apache Software License
Classifier: Operating System :: OS Independent
Requires-Python: >=3.12
License-File: LICENSE.md
License-File: NOTICE.txt
Requires-Dist: python-box~=7.3
Requires-Dist: pyyaml~=6.0
Requires-Dist: boto3~=1.35.10
Provides-Extra: dev
Requires-Dist: black~=23.7.0; extra == "dev"
Requires-Dist: docutils~=0.21; extra == "dev"
Requires-Dist: sphinx~=8.2.3; extra == "dev"
Requires-Dist: sphinx-rtd-theme==3.0.2; extra == "dev"
Requires-Dist: sphinxcontrib-googleanalytics~=0.5; extra == "dev"
Requires-Dist: mypy-zope==1.0.13; extra == "dev"
Requires-Dist: lxml-stubs==0.5.1; extra == "dev"
Requires-Dist: flake8==7.3.0; extra == "dev"
Requires-Dist: flake8-bugbear==24.12.12; extra == "dev"
Requires-Dist: flake8-docstrings==1.7.0; extra == "dev"
Requires-Dist: pep8-naming==0.12.1; extra == "dev"
Requires-Dist: mypy~=1.10.0; extra == "dev"
Requires-Dist: pydocstyle==6.1.1; extra == "dev"
Requires-Dist: coverage==5.5; extra == "dev"
Requires-Dist: pytest==6.2.5; extra == "dev"
Requires-Dist: pytest-cov==5.0.0; extra == "dev"
Requires-Dist: pytest-watch==4.2.0; extra == "dev"
Requires-Dist: pytest-xdist==2.4.0; extra == "dev"
Requires-Dist: pre-commit==2.15.0; extra == "dev"
Requires-Dist: tox~=4.11.0; extra == "dev"
Requires-Dist: types-requests~=2.31.0.20240218; extra == "dev"
Dynamic: download-url
Dynamic: license-file
